pathext/__init__.py
pathext/_chdir.py
pathext/_path_list.py
pathext/_temp.py
pathext/_util.py
pathext/_which.py
pathext/py.typed
pathext-1.5.dist-info/METADATA
pathext-1.5.dist-info/WHEEL
pathext-1.5.dist-info/licenses/LICENSE
pathext-1.5.dist-info/RECORD
