Metadata-Version: 2.4
Name: pathext
Version: 1.5
Summary: A collection of functions working with `pathlib.Path`
Project-URL: Homepage, https://github.com/petamas/python-pathext
Project-URL: Bug Tracker, https://github.com/petamas/python-pathext/issues
Author-email: Tamás PEREGI <petamas@gmail.com>
License-Expression: MIT
License-File: LICENSE
Classifier: License :: OSI Approved :: MIT License
Classifier: Operating System :: MacOS
Classifier: Operating System :: Microsoft :: Windows
Classifier: Operating System :: OS Independent
Classifier: Operating System :: POSIX
Classifier: Programming Language :: Python :: 3.10
Classifier: Programming Language :: Python :: 3.11
Classifier: Programming Language :: Python :: 3.12
Classifier: Programming Language :: Python :: 3.13
Requires-Python: >=3.10
Requires-Dist: more-itertools<11,>=10.7.0
